[
  {
    "id": "100001",
    "password": "8392"
  },
  {
    "id": "200001",
    "password": "9255"
  },
  {
    "id": "200002",
    "password": "7728"
  },
  {
    "id": "200003",
    "password": "3289"
  },
  {
    "id": "300001",
    "password": "9235"
  },
  {
    "id": "300002",
    "password": "2346"
  },
  {
    "id": "300003",
    "password": "8295"
  },
  {
    "id": "300004",
    "password": "1234"
  },
  {
    "id": "300005",
    "password": "8456"
  },
  {
    "id": "300006",
    "password": "6332"
  },
  {
    "id": "300007",
    "password": "2354"
  },
  {
    "id": "300008",
    "password": "9532"
  },
  {
    "id": "300009",
    "password": "7235"
  },
  {
    "id": "300010",
    "password": "1276"
  }
]
